sch_header/__init__.py
sch_header-1.0.0.dist-info/LICENSE
sch_header-1.0.0.dist-info/METADATA
sch_header-1.0.0.dist-info/WHEEL
sch_header-1.0.0.dist-info/top_level.txt
sch_header-1.0.0.dist-info/RECORD
