Metadata-Version: 2.1
Name: sch-header
Version: 1.0.0
Summary: HTTPS Connect header.
Home-page: UNKNOWN
Author: UNKNOWN
Author-email: UNKNOWN
License: UNKNOWN
Platform: UNKNOWN
Requires-Dist: requests
